MANIFEST.in
README.md
setup.py
django_funkymetrics.egg-info/.DS_Store
django_funkymetrics.egg-info/PKG-INFO
django_funkymetrics.egg-info/SOURCES.txt
django_funkymetrics.egg-info/dependency_links.txt
django_funkymetrics.egg-info/top_level.txt
funkymetrics/__init__.py
funkymetrics/events.py
funkymetrics/kissmetrics.py
funkymetrics/tasks.py