Metadata-Version: 1.0
Name: django-funkymetrics
Version: 0.1.7
Summary: Super simple Django application for easily tracking events and submitting them asynchronously to KISSmetrics.
Home-page: https://github.com/funkbit/django-funkymetrics
Author: Funkbit AS
Author-email: post@funkbit.no
License: BSD
Platform: UNKNOWN
Classifier: Development Status :: 4 - Beta
Classifier: Framework :: Django
Classifier: Intended Audience :: Developers
Classifier: License :: OSI Approved :: BSD License
Classifier: Programming Language :: Python
Classifier: Programming Language :: Python :: 2.6
Classifier: Programming Language :: Python :: 2.7
